mongodb_controller/__init__.py
mongodb_controller/mongodb_basis.py
mongodb_controller/mongodb_collections.py
mongodb_controller/mongodb_connector.py
mongodb_controller/mongodb_consts.py
mongodb_controller/mongodb_keys.py
mongodb_controller/mongodb_utils.py
mongodb_controller/dataset_cleanser/__init__.py
mongodb_controller/dataset_cleanser/menuESAFE500068_consts.py
mongodb_controller/dataset_cleanser/menuESAFE500068_loader.py
mongodb_controller-0.2.6.dist-info/METADATA
mongodb_controller-0.2.6.dist-info/WHEEL
mongodb_controller-0.2.6.dist-info/top_level.txt
mongodb_controller-0.2.6.dist-info/RECORD
