Metadata-Version: 2.1
Name: mongodb-controller
Version: 0.2.6
Summary: A Python module for managing fund time series data using MongoDB
Home-page: https://github.com/nailen1/mongodb_controller.git
Author: June Young Park
Author-email: juneyoungpaak@gmail.com
Keywords: mongodb database fund time-series data-management
Classifier: Development Status :: 3 - Alpha
Classifier: Intended Audience :: Developers
Classifier: Topic :: Database
Classifier: Topic :: Software Development :: Libraries :: Python Modules
Classifier: Programming Language :: Python :: 3
Classifier: Programming Language :: Python :: 3.11
Classifier: License :: OSI Approved :: MIT License
Classifier: Operating System :: OS Independent
Requires-Python: >=3.11
Requires-Dist: pymongo>=4.10.1
Requires-Dist: pandas>=2.2.3
Requires-Dist: python-dotenv>=1.0.0
Requires-Dist: aws-s3-controller>=0.7.5
Requires-Dist: shining-pebbles>=0.5.5
Requires-Dist: financial-dataset-preprocessor>=0.3.7
